Dockerfile
Dockerfile.sagemath
LICENSE
MANIFEST.in
Makefile.am
Makefile.in
README.rst
bkz.py
compile
config.guess
config.sub
configure
configure.ac
depcomp
full_sieve.py
g6k.pc.in
hkz.py
hkz_maybe.py
install-dependencies.sh
install-sh
ltmain.sh
lwe_challenge.py
missing
plain_sieve.py
requirements.txt
setup.py
svp_challenge.py
svp_exact.py
svp_exact_find_norm.py
examples/all_short_vectors.py
examples/simple_pump.py
examples/use_pump.py
g6k/__init__.py
g6k/__init__.pyc
g6k/decl.pxd
g6k/siever.cpp
g6k/siever.cpython-310-x86_64-linux-gnu.so
g6k/siever.cpython-37m-x86_64-linux-gnu.so
g6k/siever.cpython-39-x86_64-linux-gnu.so
g6k/siever.pxd
g6k/siever.pyx
g6k/siever_params.cpp
g6k/siever_params.cpython-310-x86_64-linux-gnu.so
g6k/siever_params.cpython-37m-x86_64-linux-gnu.so
g6k/siever_params.cpython-39-x86_64-linux-gnu.so
g6k/siever_params.pxd
g6k/siever_params.pyx
g6k.egg-info/PKG-INFO
g6k.egg-info/SOURCES.txt
g6k.egg-info/dependency_links.txt
g6k.egg-info/top_level.txt
g6k/__pycache__/__init__.cpython-310.pyc
g6k/__pycache__/__init__.cpython-37.pyc
g6k/__pycache__/__init__.cpython-39.pyc
g6k/algorithms/__init__.py
g6k/algorithms/bkz.py
g6k/algorithms/ducas18.py
g6k/algorithms/pump.py
g6k/algorithms/workout.py
g6k/algorithms/__pycache__/__init__.cpython-310.pyc
g6k/algorithms/__pycache__/__init__.cpython-37.pyc
g6k/algorithms/__pycache__/__init__.cpython-39.pyc
g6k/algorithms/__pycache__/bkz.cpython-310.pyc
g6k/algorithms/__pycache__/bkz.cpython-37.pyc
g6k/algorithms/__pycache__/bkz.cpython-39.pyc
g6k/algorithms/__pycache__/ducas18.cpython-310.pyc
g6k/algorithms/__pycache__/ducas18.cpython-37.pyc
g6k/algorithms/__pycache__/ducas18.cpython-39.pyc
g6k/algorithms/__pycache__/pump.cpython-310.pyc
g6k/algorithms/__pycache__/pump.cpython-37.pyc
g6k/algorithms/__pycache__/pump.cpython-39.pyc
g6k/algorithms/__pycache__/workout.cpython-310.pyc
g6k/algorithms/__pycache__/workout.cpython-37.pyc
g6k/algorithms/__pycache__/workout.cpython-39.pyc
g6k/spherical_coding/codes.py
g6k/spherical_coding/launch_all.sh
g6k/spherical_coding/sc_100_256.def
g6k/spherical_coding/sc_101_256.def
